odoo/addons/project_task_stock/README.rst
odoo/addons/project_task_stock/__init__.py
odoo/addons/project_task_stock/__manifest__.py
odoo/addons/project_task_stock/demo/project_data.xml
odoo/addons/project_task_stock/demo/stock_picking_type_data.xml
odoo/addons/project_task_stock/i18n/es.po
odoo/addons/project_task_stock/i18n/fr.po
odoo/addons/project_task_stock/i18n/hr.po
odoo/addons/project_task_stock/i18n/it.po
odoo/addons/project_task_stock/i18n/project_task_stock.pot
odoo/addons/project_task_stock/i18n/pt_BR.po
odoo/addons/project_task_stock/models/__init__.py
odoo/addons/project_task_stock/models/account_analytic_line.py
odoo/addons/project_task_stock/models/project_project.py
odoo/addons/project_task_stock/models/project_task.py
odoo/addons/project_task_stock/models/stock_move.py
odoo/addons/project_task_stock/models/stock_scrap.py
odoo/addons/project_task_stock/readme/CONFIGURE.md
odoo/addons/project_task_stock/readme/CONTRIBUTORS.md
odoo/addons/project_task_stock/readme/DESCRIPTION.md
odoo/addons/project_task_stock/readme/USAGE.md
odoo/addons/project_task_stock/static/description/icon.png
odoo/addons/project_task_stock/static/description/index.html
odoo/addons/project_task_stock/tests/__init__.py
odoo/addons/project_task_stock/tests/common.py
odoo/addons/project_task_stock/tests/test_project_task_stock.py
odoo/addons/project_task_stock/views/project_project_view.xml
odoo/addons/project_task_stock/views/project_task_type_view.xml
odoo/addons/project_task_stock/views/project_task_view.xml
odoo/addons/project_task_stock/views/stock_move_view.xml
odoo/addons/project_task_stock/views/stock_scrap_views.xml
odoo_addon_project_task_stock-18.0.1.0.1.dist-info/METADATA
odoo_addon_project_task_stock-18.0.1.0.1.dist-info/WHEEL
odoo_addon_project_task_stock-18.0.1.0.1.dist-info/top_level.txt
odoo_addon_project_task_stock-18.0.1.0.1.dist-info/RECORD
